{"version":1,"resource":"file:///home/hrishikesh/Documents/Coding/javaScript/30Days/JS30Days/Day_05/style.css","entries":[{"id":"MzgY.css","timestamp":1718127518044},{"id":"zdhC.css","source":"undoRedo.source","timestamp":1718127522584},{"id":"ewi8.css","timestamp":1718127550423},{"id":"e36q.css","timestamp":1718127568631},{"id":"1vPW.css","timestamp":1718127615919},{"id":"MssM.css","timestamp":1718127662099},{"id":"MI2U.css","timestamp":1718127716502},{"id":"fC50.css","timestamp":1718127762058},{"id":"UDBm.css","timestamp":1718127773870},{"id":"0stD.css","timestamp":1718127789750},{"id":"6Jks.css","timestamp":1718127817385},{"id":"Cw9T.css","source":"undoRedo.source","timestamp":1718127827105},{"id":"FC3c.css","timestamp":1718127843741},{"id":"tLj9.css","source":"undoRedo.source","timestamp":1718127846837},{"id":"rttU.css","timestamp":1718127849281},{"id":"xUdO.css","timestamp":1718127874617},{"id":"GqKe.css","timestamp":1718127914913},{"id":"OxKl.css","source":"undoRedo.source","timestamp":1718127935440},{"id":"SUzV.css","timestamp":1718127950796},{"id":"TT7L.css","timestamp":1718128019300},{"id":"CfxE.css","timestamp":1718128056471},{"id":"QEjn.css","timestamp":1718128111703},{"id":"55zx.css","timestamp":1718128144547},{"id":"aBFZ.css","timestamp":1718128776403},{"id":"MzX8.css","timestamp":1718128788103},{"id":"jU31.css","source":"undoRedo.source","timestamp":1718128792567},{"id":"I3iv.css","timestamp":1718128804111},{"id":"jepn.css","source":"undoRedo.source","timestamp":1718128807987},{"id":"E98X.css","timestamp":1718128826199},{"id":"2JXT.css","timestamp":1718128844311},{"id":"BsXZ.css","timestamp":1718128896375},{"id":"yUoa.css","timestamp":1718128932916},{"id":"7Kqe.css","timestamp":1718128977764},{"id":"Pne0.css","timestamp":1718129012288},{"id":"CUJ7.css","timestamp":1718129092860},{"id":"wHc8.css","timestamp":1718129121740},{"id":"ffHJ.css","timestamp":1718129143460},{"id":"jFRp.css","timestamp":1718129166476},{"id":"emwm.css","timestamp":1718129192276},{"id":"g0tx.css","timestamp":1718129303488},{"id":"XXs8.css","timestamp":1718129355592},{"id":"catL.css","source":"undoRedo.source","timestamp":1718129357596},{"id":"fMql.css","timestamp":1718129362968},{"id":"FD9T.css","timestamp":1718129428051},{"id":"v6Ox.css","timestamp":1718129462403},{"id":"UoF2.css","timestamp":1718129492935},{"id":"IkOH.css","timestamp":1718129525567},{"id":"hOsl.css","timestamp":1718129576195},{"id":"sZdZ.css","timestamp":1718129586955},{"id":"pGYM.css","timestamp":1718129602775}]}